{
  "TemplateID": 44171,
  "Inventory": [
    77577,
    77614,
    87882,
    87881,
    87883,
    87884,
    87878,
    87879,
    77617,
    87880,
    77573,
    77619,
    77570,
    77582,
    77591,
    77598,
    77605,
    77612
  ],
  "@metadata": {
    "@collection": "NpcInventory",
    "Raven-Clr-Type": "DragonNPCTool.Models.NPCInventory, DragonNPCTool",
    "@change-vector": "A:3027-W9pQo7ze7EWvihr0j0wlRg",
    "@id": "NPCInventories/257-A",
    "@last-modified": "2024-03-10T06:04:19.1924084Z"
  }
}
