{
  "ZoneName": "DragonSpire/DS_A3_Kings/Interiors/DS_Crystal_T1",
  "Events": [],
  "Teleports": [
    {
      "TriggerName": "Teleport location (DS_T1 to CrystalGrove)",
      "Teleport": {
        "m_exitTeleporter": 0,
        "m_teleporterTag": 0,
        "m_teleportType": "TELEPORT_STATIC",
        "m_transitionID": 0,
        "m_destinationLoc": "-22529.59,29680.63,180.0048,0",
        "m_destinationZone": "DragonSpire/DS_A3_Kings/DS_A3Z1_CrystalGrove"
      }
    }
  ],
  "@metadata": {
    "@collection": "ZoneTransfer",
    "Raven-Clr-Type": "DragonZoneTool.Models.WizardZoneData, DragonZoneTool",
    "@change-vector": "A:2292-W9pQo7ze7EWvihr0j0wlRg",
    "@id": "WizardZoneDatas/10753-A",
    "@last-modified": "2023-11-26T05:43:17.3370986Z"
  }
}
