{
  "ZoneName": "WizardCity/WC_Streets/WC_Triton_Underwater/Interiors/WC_Triton_Underwater_C1",
  "Events": [],
  "Teleports": [
    {
      "TriggerName": "BackToTU",
      "Teleport": {
        "m_exitTeleporter": 0,
        "m_teleporterTag": 0,
        "m_teleportType": "TELEPORT_STATIC",
        "m_transitionID": 0,
        "m_destinationLoc": "-10172.11,-1760.865,162.3403,-1.490668",
        "m_destinationZone": "WizardCity/WC_Streets/WC_Triton_Underwater/WC_Triton_Underwater"
      }
    }
  ]
}
