{
  "ZoneName": "Housing_GHGauntlet/GH_WinterbaneGauntlet01/GH_WinterbaneGauntlet01_R01",
  "Events": [],
  "Teleports": [
    {
      "TriggerName": "Room2TeleportTrigger (1)",
      "Teleport": {
        "m_exitTeleporter": 0,
        "m_teleporterTag": 0,
        "m_teleportType": "TELEPORT_STATIC",
        "m_transitionID": 0,
        "m_destinationLoc": "-2328.243,-20.01977,15.09207,-1.504228",
        "m_destinationZone": "Housing_GHGauntlet/GH_WinterbaneGauntlet01/GH_WinterbaneGauntlet01_R02"
      }
    }
  ]
}
